pss_scrambler/__main__.py
pss_scrambler/dictionary.py
pss_scrambler/pss_keywords.py
pss_scrambler/translator.py
pss_scrambler/cmds/cmd_encode.py
pss_scrambler-0.0.2.4632135087.dist-info/LICENSE
pss_scrambler-0.0.2.4632135087.dist-info/METADATA
pss_scrambler-0.0.2.4632135087.dist-info/WHEEL
pss_scrambler-0.0.2.4632135087.dist-info/entry_points.txt
pss_scrambler-0.0.2.4632135087.dist-info/top_level.txt
pss_scrambler-0.0.2.4632135087.dist-info/RECORD
