Metadata-Version: 2.1
Name: pss-scrambler
Version: 0.0.2.4632135087
Summary: PSS Scrambler replaces user-specified identifiers with random names.
Home-page: https://github.com/psstools/pss-scrambler
Author: Matthew Ballance
Author-email: matt.ballance@gmail.com
License: Apache 2.0
Keywords: PSS,Portable Test and Stimulus,obfuscator
License-File: LICENSE
